AUTHORS.rst
CONTRIBUTING.rst
HISTORY.rst
LICENSE
MANIFEST.in
README.rst
setup.cfg
setup.py
docs/Makefile
docs/authors.rst
docs/conf.py
docs/contributing.rst
docs/history.rst
docs/index.rst
docs/installation.rst
docs/make.bat
docs/readme.rst
docs/usage.rst
pyclist/__init__.py
pyclist/example.py
pyclist/example_json.py
pyclist/model_helpers.py
pyclist/pyclist.py
pyclist.egg-info/PKG-INFO
pyclist.egg-info/SOURCES.txt
pyclist.egg-info/dependency_links.txt
pyclist.egg-info/entry_points.txt
pyclist.egg-info/not-zip-safe
pyclist.egg-info/requires.txt
pyclist.egg-info/top_level.txt
tests/__init__.py
tests/test_pyclist.py