Metadata-Version: 1.1
Name: pyclist
Version: 0.2.6
Summary: Makes creating cli wrappers for rest services easier.
Home-page: https://github.com/makkus/pyclist
Author: Markus Binsteiner
Author-email: makkus@gmail.com
License: ISCL
Keywords: pyclist
Platform: UNKNOWN
Classifier: Development Status :: 2 - Pre-Alpha
Classifier: Intended Audience :: Developers
Classifier: License :: OSI Approved :: ISC License (ISCL)
Classifier: Natural Language :: English
Classifier: Programming Language :: Python :: 2
Classifier: Programming Language :: Python :: 2.6
Classifier: Programming Language :: Python :: 2.7
Classifier: Programming Language :: Python :: 3
Classifier: Programming Language :: Python :: 3.3
Classifier: Programming Language :: Python :: 3.4
